odoo/addons/fieldservice_equipment_stock_return/README.rst
odoo/addons/fieldservice_equipment_stock_return/__init__.py
odoo/addons/fieldservice_equipment_stock_return/__manifest__.py
odoo/addons/fieldservice_equipment_stock_return/data/fsm_order_type.xml
odoo/addons/fieldservice_equipment_stock_return/i18n/fieldservice_equipment_stock_return.pot
odoo/addons/fieldservice_equipment_stock_return/i18n/fr.po
odoo/addons/fieldservice_equipment_stock_return/i18n/it.po
odoo/addons/fieldservice_equipment_stock_return/models/__init__.py
odoo/addons/fieldservice_equipment_stock_return/models/fsm_equipment.py
odoo/addons/fieldservice_equipment_stock_return/models/fsm_order.py
odoo/addons/fieldservice_equipment_stock_return/models/fsm_order_type.py
odoo/addons/fieldservice_equipment_stock_return/readme/CONFIGURE.md
odoo/addons/fieldservice_equipment_stock_return/readme/CONTRIBUTORS.md
odoo/addons/fieldservice_equipment_stock_return/readme/CREDITS.md
odoo/addons/fieldservice_equipment_stock_return/readme/DESCRIPTION.md
odoo/addons/fieldservice_equipment_stock_return/readme/USAGE.md
odoo/addons/fieldservice_equipment_stock_return/static/description/icon.png
odoo/addons/fieldservice_equipment_stock_return/static/description/index.html
odoo/addons/fieldservice_equipment_stock_return/tests/__init__.py
odoo/addons/fieldservice_equipment_stock_return/tests/test_fsm_equipment_return.py
odoo/addons/fieldservice_equipment_stock_return/views/fsm_equipment.xml
odoo/addons/fieldservice_equipment_stock_return/views/fsm_order_type_view.xml
odoo/addons/fieldservice_equipment_stock_return/views/fsm_order_view.xml
odoo_addon_fieldservice_equipment_stock_return-17.0.1.0.0.4.dist-info/METADATA
odoo_addon_fieldservice_equipment_stock_return-17.0.1.0.0.4.dist-info/WHEEL
odoo_addon_fieldservice_equipment_stock_return-17.0.1.0.0.4.dist-info/top_level.txt
odoo_addon_fieldservice_equipment_stock_return-17.0.1.0.0.4.dist-info/RECORD
